strands_bitchat/__init__.py
strands_bitchat/bitchat.py
strands_bitchat-1.0.7.dist-info/licenses/LICENSE
strands_bitchat-1.0.7.dist-info/METADATA
strands_bitchat-1.0.7.dist-info/WHEEL
strands_bitchat-1.0.7.dist-info/entry_points.txt
strands_bitchat-1.0.7.dist-info/top_level.txt
strands_bitchat-1.0.7.dist-info/RECORD
