Metadata-Version: 2.4
Name: strands-bitchat
Version: 1.0.7
Summary: Decentralized P2P Encrypted Chat Agent powered by Strands Agents & Bluetooth LE
Home-page: https://github.com/cagataycali/strands-bitchat
Author: Cagatay Cali
Author-email: Cagatay Cali <cagataycali@icloud.com>
Maintainer: Cagatay Cali
Maintainer-email: Cagatay Cali <cagataycali@icloud.com>
License: MIT
Project-URL: Homepage, https://github.com/cagataycali/strands-bitchat
Project-URL: Documentation, https://github.com/cagataycali/strands-bitchat#readme
Project-URL: Repository, https://github.com/cagataycali/strands-bitchat
Project-URL: Bug Tracker, https://github.com/cagataycali/strands-bitchat/issues
Keywords: strands-agents,ai-agent,bitchat,p2p,bluetooth,encryption,mesh-network,decentralized,privacy,secure-chat,noise-protocol,ble,agent-to-agent,offline-communication
Platform: any
Classifier: Development Status :: 4 - Beta
Classifier: Intended Audience :: Developers
Classifier: Intended Audience :: Information Technology
Classifier: Intended Audience :: Science/Research
Classifier: License :: OSI Approved :: MIT License
Classifier: Operating System :: OS Independent
Classifier: Operating System :: POSIX :: Linux
Classifier: Operating System :: MacOS
Classifier: Operating System :: Microsoft :: Windows
Classifier: Programming Language :: Python :: 3
Classifier: Programming Language :: Python :: 3.8
Classifier: Programming Language :: Python :: 3.9
Classifier: Programming Language :: Python :: 3.10
Classifier: Programming Language :: Python :: 3.11
Classifier: Programming Language :: Python :: 3.12
Classifier: Topic :: Communications :: Chat
Classifier: Topic :: Internet
Classifier: Topic :: Security :: Cryptography
Classifier: Topic :: Software Development :: Libraries :: Python Modules
Classifier: Topic :: System :: Networking
Classifier: Topic :: Scientific/Engineering :: Artificial Intelligence
Requires-Python: >=3.10
License-File: LICENSE
Requires-Dist: strands-agents
Requires-Dist: strands-agents[ollama]
Requires-Dist: strands-agents-tools
Requires-Dist: bleak>=0.20.0
Requires-Dist: pybloom-live>=4.0.0
Requires-Dist: lz4>=4.3.0
Requires-Dist: aioconsole>=0.6.0
Requires-Dist: cryptography>=41.0.0
Provides-Extra: dev
Requires-Dist: pytest>=7.0.0; extra == "dev"
Requires-Dist: pytest-asyncio>=0.21.0; extra == "dev"
Requires-Dist: black>=22.0.0; extra == "dev"
Requires-Dist: flake8>=4.0.0; extra == "dev"
Requires-Dist: mypy>=0.950; extra == "dev"
Requires-Dist: twine>=4.0.0; extra == "dev"
Requires-Dist: build>=0.8.0; extra == "dev"
Provides-Extra: docs
Requires-Dist: sphinx>=4.0.0; extra == "docs"
Requires-Dist: sphinx-rtd-theme>=1.0.0; extra == "docs"
Requires-Dist: myst-parser>=0.18.0; extra == "docs"
Dynamic: author
Dynamic: home-page
Dynamic: license-file
Dynamic: maintainer
Dynamic: platform
Dynamic: requires-python
